setup.py
wrap_amqp.py
wrap_amqp.egg-info/PKG-INFO
wrap_amqp.egg-info/SOURCES.txt
wrap_amqp.egg-info/dependency_links.txt
wrap_amqp.egg-info/requires.txt
wrap_amqp.egg-info/top_level.txt