Metadata-Version: 1.0
Name: wrap-amqp
Version: 1.0.4
Summary: a wrapper for amqp
Home-page: http://tieba.baidu.com/f?ie=utf-8&kw=%E5%91%A8%E4%BA%95%E6%B1%9F
Author: timchow
Author-email: jordan23nbastar@yeah.net
License: LGPL
Keywords: amqp wrapper kombu
Platform: UNKNOWN
